new_print_function/__init__.py
new_print_function/format.py
new_print_function/print.py
new_print_function/colors/__init__.py
new_print_function/colors/colors.py
new_print_function/colors/shades/__init__.py
new_print_function/colors/shades/blues.py
new_print_function/colors/shades/browns.py
new_print_function/colors/shades/greens.py
new_print_function/colors/shades/greys.py
new_print_function/colors/shades/oranges.py
new_print_function/colors/shades/pinks.py
new_print_function/colors/shades/purples.py
new_print_function/colors/shades/reds.py
new_print_function/colors/shades/whites.py
new_print_function/colors/shades/yellows.py
new_print_function/font_styles/__init__.py
new_print_function/font_styles/font_styles.py
new_print_function/literals/__init__.py
new_print_function/literals/colors.py
new_print_function/literals/font_styles.py
new_print_function-1.0.0.dist-info/LICENSE
new_print_function-1.0.0.dist-info/METADATA
new_print_function-1.0.0.dist-info/WHEEL
new_print_function-1.0.0.dist-info/top_level.txt
new_print_function-1.0.0.dist-info/RECORD
