Metadata-Version: 2.1
Name: new_print_function
Version: 1.0.0
Summary: The New Python Print Function.
Author-email: "Haripo Wesley T." <haripowesleyt@proton.me>
Maintainer-email: "Haripo Wesley T." <haripowesleyt@proton.me>
Project-URL: Homepage, https://github.com/pypa/new_print_function
Project-URL: Issues, https://github.com/pypa/new_print_function/issues
Project-URL: Repository, https://github.com/haripowesleyt/new_print_function/
Keywords: new print function,color print,background color,font style,foreground color,terminal color
Classifier: Development Status :: 5 - Production/Stable
Classifier: Intended Audience :: Developers
Classifier: Programming Language :: Python :: 3
Classifier: License :: OSI Approved :: MIT License
Classifier: Operating System :: OS Independent
Requires-Python: >=3.0
License-File: LICENSE
